user_behavior/__init__.py
user_behavior/admin/__init__.py
user_behavior/admin/page_view.py
user_behavior/admin/user_interaction.py
user_behavior/admin/user_session.py
user_behavior/api/__init__.py
user_behavior/api/filters/__init__.py
user_behavior/api/filters/page_view.py
user_behavior/api/filters/user_interaction.py
user_behavior/api/filters/user_session.py
user_behavior/api/paginations/__init__.py
user_behavior/api/paginations/limit_offset_pagination.py
user_behavior/api/permissions/__init__.py
user_behavior/api/serializers/__init__.py
user_behavior/api/serializers/helper/get_serializer_cls.py
user_behavior/api/serializers/page_view.py
user_behavior/api/serializers/user_interaction.py
user_behavior/api/serializers/user_session.py
user_behavior/api/throttlings/__init__.py
user_behavior/api/throttlings/role_base_throttle.py
user_behavior/api/views/__init__.py
user_behavior/api/views/base.py
user_behavior/api/views/page_view.py
user_behavior/api/views/user_interaction.py
user_behavior/api/views/user_session.py
user_behavior/apps.py
user_behavior/constants/__init__.py
user_behavior/constants/default_settings.py
user_behavior/constants/types.py
user_behavior/migrations/0001_initial.py
user_behavior/migrations/__init__.py
user_behavior/mixins/__init__.py
user_behavior/mixins/admin/__init__.py
user_behavior/mixins/admin/permission.py
user_behavior/mixins/api/__init__.py
user_behavior/mixins/api/config_api_attrs.py
user_behavior/mixins/api/control_api_methods.py
user_behavior/models/__init__.py
user_behavior/models/helper/enum/event_type.py
user_behavior/models/page_view.py
user_behavior/models/user_interaction.py
user_behavior/models/user_session.py
user_behavior/settings/__init__.py
user_behavior/settings/checks.py
user_behavior/settings/conf.py
user_behavior/signals/__init__.py
user_behavior/signals/models.py
user_behavior/static/css/report.css
user_behavior/static/images/lazarus.png
user_behavior/static/images/stream.png
user_behavior/templates/report.html
dj_user_behavior-1.0.0.dist-info/AUTHORS.md
dj_user_behavior-1.0.0.dist-info/LICENSE
dj_user_behavior-1.0.0.dist-info/METADATA
dj_user_behavior-1.0.0.dist-info/WHEEL
dj_user_behavior-1.0.0.dist-info/RECORD
